enarguswiki/__init__.py
enarguswiki/__main__.py
enarguswiki/core.py
enarguswiki-0.2.0.dist-info/LICENSE.md
enarguswiki-0.2.0.dist-info/METADATA
enarguswiki-0.2.0.dist-info/WHEEL
enarguswiki-0.2.0.dist-info/entry_points.txt
enarguswiki-0.2.0.dist-info/RECORD
