Metadata-Version: 2.1
Name: enarguswiki
Version: 0.2.0
Summary: Small CLI to fetch the EnArgus Wiki
License: CC-BY-SA-4.0
Author: Daniel Müller
Author-email: acct.d-mueller@mailbox.org
Requires-Python: >=3.11,<4
Classifier: License :: Other/Proprietary License
Classifier: Programming Language :: Python :: 3
Classifier: Programming Language :: Python :: 3.11
Classifier: Programming Language :: Python :: 3.12
Requires-Dist: html5lib (>=1.1,<2.0)
Requires-Dist: pydantic (>=2.7.4,<3.0.0)
Requires-Dist: python-slugify (>=8.0.4,<9.0.0)
Requires-Dist: requests (>=2.32.3,<3.0.0)
Requires-Dist: typer (>=0.12.3,<0.13.0)
Requires-Dist: xhtml2pdf (>=0.2.16,<0.3.0)
